AUTHORS
LICENSE
MANIFEST.in
README.rst
setup.py
Djax.egg-info/PKG-INFO
Djax.egg-info/SOURCES.txt
Djax.egg-info/dependency_links.txt
Djax.egg-info/requires.txt
Djax.egg-info/top_level.txt
djax/__init__.py
djax/content.py
djax/decorators.py
djax/gateway.py
djax/middleware.py
djax/models.py
djax/registry.py
djax/tasks.py
djax/triggers.py
djax/urls.py
djax/views.py
djax/management/__init__.py
djax/management/commands/__init__.py
djax/management/commands/add_content_record.py
djax/management/commands/clear_content_sync_locks.py
djax/management/commands/list_auth_tokens.py
djax/management/commands/make_auth_token.py
djax/management/commands/revoke_auth_token.py
djax/management/commands/sync_axilent.py
pax/__init__.py
pax/calendar.py
pax/client.py
pax/content.py
pax/exceptions.py
pax/library.py
pax/messaging.py
pax/triggers.py
pax/util.py