Metadata-Version: 1.1
Name: Djax
Version: 0.8.3
Summary: Integrates Django projects with Axilent.
Home-page: http://github.com/Axilent/Djax
Author: Loren Davie
Author-email: code@axilent.com
License: BSD
Platform: UNKNOWN
Classifier: Development Status :: 3 - Alpha
Classifier: Environment :: Web Environment
Classifier: Intended Audience :: Developers
Classifier: License :: OSI Approved :: BSD License
Classifier: Programming Language :: Python
Classifier: Topic :: Software Development :: Libraries :: Python Modules
